{
  "poems": [
    "Robert Browning|Why I am a Liberal",
    "Robert Browning|In a Gondola",
    "Alexander Pope|Messiah.",
    "Emily Dickinson|Glass was the Street -- in tinsel Peril",
    "Walt Whitman|From Paumanok Starting.",
    "George Gordon, Lord Byron|Heaven and Earth",
    "John Milton|Paradise Lost: Book 10",
    "Robert Burns|247. Ode, Sacred to the Memory of Mrs. Oswald of Auchencruive",
    "Edgar Allan Poe|Eldorado",
    "George Gordon, Lord Byron|Sonnet to Lake Leman",
    "Robert Browning|Abt Vogler: After he has been extemporizing upon the musical instrument of his invention",
    "John Dryden|Absalom And Achitophel",
    "Edward Thomas|Wind and Mist",
    "Geoffrey Chaucer|The Canterbury Tales. The Sompnour's Tale.",
    "Percy Bysshe Shelley|Epipsychidion"
  ],
  "artworks": [
    "156461",
    "262253",
    "128208",
    "207204",
    "270314",
    "76747",
    "50155",
    "134452",
    "272045",
    "91180",
    "13527",
    "254311",
    "269504",
    "58175"
  ],
  "essays": [
    "essay-003",
    "essay-015",
    "essay-007",
    "essay-019",
    "essay-008",
    "essay-013",
    "essay-010",
    "essay-020",
    "essay-002",
    "essay-018",
    "essay-011",
    "essay-005",
    "essay-024",
    "essay-023",
    "essay-009"
  ],
  "stories": [
    "story-015",
    "story-012",
    "story-011",
    "story-020",
    "story-006",
    "story-021",
    "story-013",
    "story-008",
    "story-003",
    "story-001",
    "story-016",
    "story-005",
    "story-019",
    "story-009",
    "story-023"
  ],
  "life_lessons": [
    "lesson-010",
    "lesson-018",
    "lesson-003",
    "lesson-022",
    "lesson-009",
    "lesson-004",
    "lesson-013",
    "lesson-001",
    "lesson-020",
    "lesson-025",
    "lesson-021",
    "lesson-012",
    "lesson-008",
    "lesson-023",
    "lesson-005"
  ]
}