{
  "poems": [
    "Robert Browning|Why I am a Liberal",
    "Robert Browning|In a Gondola",
    "Alexander Pope|Messiah.",
    "Emily Dickinson|Glass was the Street -- in tinsel Peril",
    "Walt Whitman|From Paumanok Starting.",
    "George Gordon, Lord Byron|Heaven and Earth",
    "John Milton|Paradise Lost: Book 10",
    "Robert Burns|247. Ode, Sacred to the Memory of Mrs. Oswald of Auchencruive",
    "Edgar Allan Poe|Eldorado",
    "George Gordon, Lord Byron|Sonnet to Lake Leman",
    "Robert Browning|Abt Vogler: After he has been extemporizing upon the musical instrument of his invention",
    "John Dryden|Absalom And Achitophel",
    "Edward Thomas|Wind and Mist",
    "Geoffrey Chaucer|The Canterbury Tales. The Sompnour's Tale.",
    "Percy Bysshe Shelley|Epipsychidion",
    "Emma Lazarus|Success",
    "Geoffrey Chaucer|The Canterbury Tales. The Prioress's Tale.",
    "Percy Bysshe Shelley|Prince Athanase.  a Fragment",
    "Geoffrey Chaucer|The Canterbury Tales. The Friar's Tale.",
    "George Gordon, Lord Byron|Lines Written in an Album, at Malta",
    "Emily Dickinson|Summer laid her simple Hat",
    "Robert Burns|79. Adam Armour\u2019s Prayer",
    "Geoffrey Chaucer|The Canterbury Tales. The Doctor's Tale.",
    "John Wilmot|A Letter from Artemesia in the Town to Chloe in the Country",
    "Alexander Pope|Two Choruses to the Tragedy of Brutus.",
    "Lord Alfred Tennyson|The Progress of Spring",
    "Percy Bysshe Shelley|Homer's Hymn to Venus",
    "George Gordon, Lord Byron|Stanzas Written in Passing the Ambracian Gulf",
    "Percy Bysshe Shelley|To --",
    "John Dryden|Mac Flecknoe",
    "John Milton|Paradise Lost: Book 08",
    "William Cowper|The Christian",
    "Edward Thomas|The Path",
    "George Gordon, Lord Byron|Manfred: A Dramatic Poem",
    "Alexander Pope|Epitaph. Intended for Mr Rowe, in Westminster Abbey.",
    "William Blake|A LITTLE GIRL LOST",
    "Geoffrey Chaucer|The Canterbury Tales. The Reeve's Tale.",
    "George Gordon, Lord Byron|The Vision of Judgment.  by Quevedo Redivivus",
    "George Gordon, Lord Byron|Stanzas to Jessy",
    "Andrew Marvell|The Picture Of Little T.C. In A Prospect Of Flowers",
    "George Gordon, Lord Byron|Sardanapalus",
    "Emily Dickinson|A Drop Fell on the Apple Tree --",
    "Algernon Charles Swinburne|To Walt Whitman In America",
    "Geoffrey Chaucer|Troilus and Criseyde: Book IV",
    "Charlotte Smith|Sonnet XLIV: Press'd by the Moon",
    "George Gordon, Lord Byron|The Age of Bronze",
    "Percy Bysshe Shelley|Adonais",
    "George Gordon, Lord Byron|Lara. ",
    "George Gordon, Lord Byron|To Dives. a Fragment",
    "Robert Browning|Prospice",
    "Alexander Pope|Epistle to James Craggs, Esq., Secretary of State.",
    "Percy Bysshe Shelley|To Death"
  ],
  "artworks": [
    "156461",
    "262253",
    "128208",
    "207204",
    "270314",
    "76747",
    "50155",
    "134452",
    "272045",
    "91180",
    "13527",
    "254311",
    "269504",
    "58175",
    "147055",
    "63073",
    "127867",
    "230708",
    "19456",
    "90446",
    "78547",
    "159096",
    "185760",
    "59656",
    "274216",
    "189116",
    "46271",
    "117475",
    "230692",
    "222984",
    "202944",
    "109173",
    "4183",
    "150868",
    "150054",
    "69036",
    "130622",
    "145903",
    "152740",
    "35184",
    "105549",
    "99653",
    "251152",
    "24042",
    "3609",
    "12725",
    "265982",
    "62271",
    "9516",
    "131335",
    "145272",
    "83905",
    "65814"
  ],
  "essays": [
    "essay-008",
    "essay-010",
    "essay-021",
    "essay-007"
  ],
  "stories": [
    "story-016",
    "story-005",
    "story-003",
    "story-001"
  ],
  "life_lessons": [
    "lesson-002",
    "lesson-016",
    "lesson-003",
    "lesson-007"
  ]
}